[
  {
    "id": "2b69c00a-2f53-474c-9c3a-746197e93361",
    "data": [
      {
        "text": "end",
        "userDefined": false
      }
    ],
    "isTemplate": false,
    "count": 0,
    "lang": "en",
    "updated": 0
  },
  {
    "id": "09cfae27-7e5f-4f37-8494-2310d6c9a490",
    "data": [
      {
        "text": "over n out",
        "userDefined": false
      }
    ],
    "isTemplate": false,
    "count": 0,
    "lang": "en",
    "updated": 0
  },
  {
    "id": "a54d86d3-d530-4359-a992-d987cc361a71",
    "data": [
      {
        "text": "cancel",
        "userDefined": false
      }
    ],
    "isTemplate": false,
    "count": 0,
    "lang": "en",
    "updated": 0
  },
  {
    "id": "9235b076-eb4b-46d2-b517-ce2a641b1e7b",
    "data": [
      {
        "text": "see you soon",
        "userDefined": false
      }
    ],
    "isTemplate": false,
    "count": 0,
    "lang": "en",
    "updated": 0
  },
  {
    "id": "9c5bcff5-a159-40b6-8294-f20ae24c97eb",
    "data": [
      {
        "text": "bye",
        "userDefined": false
      }
    ],
    "isTemplate": false,
    "count": 0,
    "lang": "en",
    "updated": 0
  },
  {
    "id": "1f9b5dd6-b6eb-469a-8e01-a4af173be815",
    "data": [
      {
        "text": "good bye",
        "userDefined": false
      }
    ],
    "isTemplate": false,
    "count": 0,
    "lang": "en",
    "updated": 0
  }
]